Metadata-Version: 1.0
Name: jdg-13-distributions
Version: 0.1
Summary: Gaussian distributions
Home-page: UNKNOWN
Author: Joshua Glenn
Author-email: jdglenn_13@yahoo.com
License: UNKNOWN
Platform: UNKNOWN
